filex/__init__.py
filex/core.py
filex/exceptions.py
py_filex-1.0.0.dist-info/licenses/LICENSE
tests/__init__.py
tests/test_dir.py
tests/test_file.py
tests/test_utils.py
py_filex-1.0.0.dist-info/METADATA
py_filex-1.0.0.dist-info/WHEEL
py_filex-1.0.0.dist-info/top_level.txt
py_filex-1.0.0.dist-info/RECORD
