Metadata-Version: 2.4
Name: py-filex
Version: 1.0.0
Summary: Gestion intelligente des fichiers et dossiers en Python
Home-page: https://github.com/Moesthetics-code/py-filex
Author: Mohamed Ndiaye
Author-email: Mohamed Ndiaye <mintok2000@gmail.com>
License: MIT
Project-URL: Homepage, https://github.com/Moesthetics-code/py-filex
Project-URL: Repository, https://github.com/Moesthetics-code/py-filex.git
Project-URL: Issues, https://github.com/Moesthetics-code/py-filex/issues
Keywords: file,directory,filesystem,utility,management
Classifier: Development Status :: 5 - Production/Stable
Classifier: Intended Audience :: Developers
Classifier: License :: OSI Approved :: MIT License
Classifier: Operating System :: OS Independent
Classifier: Programming Language :: Python :: 3
Classifier: Programming Language :: Python :: 3.7
Classifier: Programming Language :: Python :: 3.8
Classifier: Programming Language :: Python :: 3.9
Classifier: Programming Language :: Python :: 3.10
Classifier: Programming Language :: Python :: 3.11
Requires-Python: >=3.7
License-File: LICENSE
Provides-Extra: dev
Requires-Dist: pytest>=6.0; extra == "dev"
Requires-Dist: pytest-cov>=2.0; extra == "dev"
Requires-Dist: black>=21.0; extra == "dev"
Requires-Dist: flake8>=3.9; extra == "dev"
Requires-Dist: mypy>=0.900; extra == "dev"
Dynamic: author
Dynamic: home-page
Dynamic: license-file
Dynamic: requires-python
